azureml/__init__.py
azureml/evaluate/__init__.py
azureml/evaluate/mlflow/NOTICE
azureml/evaluate/mlflow/__init__.py
azureml/evaluate/mlflow/_version.py
azureml/evaluate/mlflow/constants.py
azureml/evaluate/mlflow/exceptions.py
azureml/evaluate/mlflow/_loader_modules/__init__.py
azureml/evaluate/mlflow/_loader_modules/hftransformers.py
azureml/evaluate/mlflow/_loader_modules/sklearn.py
azureml/evaluate/mlflow/aml/__init__.py
azureml/evaluate/mlflow/aml/constants.py
azureml/evaluate/mlflow/aml/model.py
azureml/evaluate/mlflow/aml/utils.py
azureml/evaluate/mlflow/hftransformers/__init__.py
azureml/evaluate/mlflow/hftransformers/_task_based_pipeline_predictors.py
azureml/evaluate/mlflow/hftransformers/_task_based_predictors.py
azureml/evaluate/mlflow/hftransformers/constants.py
azureml/evaluate/mlflow/hftransformers/ner_pipeline.py
azureml/evaluate/mlflow/hftransformers/utils.py
azureml/evaluate/mlflow/models/__init__.py
azureml/evaluate/mlflow/models/evaluation/__init__.py
azureml/evaluate/mlflow/models/evaluation/base.py
azureml/evaluate/mlflow/models/evaluation/constants.py
azureml/evaluate/mlflow/models/evaluation/default_evaluator.py
azureml/evaluate/mlflow/models/evaluation/evaluator_registry.py
azureml/evaluate/mlflow/models/evaluation/azureml/__init__.py
azureml/evaluate/mlflow/models/evaluation/azureml/_classifier_evaluator.py
azureml/evaluate/mlflow/models/evaluation/azureml/_classifier_multilabel_evaluator.py
azureml/evaluate/mlflow/models/evaluation/azureml/_fill_mask_evaluator.py
azureml/evaluate/mlflow/models/evaluation/azureml/_forecaster_evaluator.py
azureml/evaluate/mlflow/models/evaluation/azureml/_image_classifier_evaluator.py
azureml/evaluate/mlflow/models/evaluation/azureml/_image_od_is_evaluator.py
azureml/evaluate/mlflow/models/evaluation/azureml/_ner_evaluator.py
azureml/evaluate/mlflow/models/evaluation/azureml/_qna_evaluator.py
azureml/evaluate/mlflow/models/evaluation/azureml/_regressor_evaluator.py
azureml_evaluate_mlflow-47.0.0.dist-info/LICENSE.txt
azureml_evaluate_mlflow-47.0.0.dist-info/METADATA
azureml_evaluate_mlflow-47.0.0.dist-info/WHEEL
azureml_evaluate_mlflow-47.0.0.dist-info/top_level.txt
azureml_evaluate_mlflow-47.0.0.dist-info/RECORD
