Metadata-Version: 2.1
Name: azureml-evaluate-mlflow
Version: 47.0.0
Summary: Contains the integration code of AzureML Evaluate with Mlflow.
Home-page: 
Author: Microsoft Corp
License: Proprietary https://aka.ms/azureml-preview-sdk-license 
Classifier: Development Status :: 4 - Beta
Classifier: Intended Audience :: Developers
Classifier: Intended Audience :: Science/Research
Classifier: License :: Other/Proprietary License
Classifier: Programming Language :: Python :: 3
Classifier: Programming Language :: Python :: 3.6
Classifier: Programming Language :: Python :: 3.7
Classifier: Programming Language :: Python :: 3.8
Classifier: Programming Language :: Python :: 3.9
Classifier: Programming Language :: Python :: 3.10
Classifier: Topic :: Scientific/Engineering :: Artificial Intelligence
Classifier: Operating System :: Microsoft :: Windows
Classifier: Operating System :: MacOS
Classifier: Operating System :: POSIX :: Linux
Requires-Python: >=3.8,<4.0
License-File: LICENSE.txt
Requires-Dist: jsonpickle
Requires-Dist: mlflow ==2.10.2
Requires-Dist: mlflow-skinny ==2.10.2
Requires-Dist: azureml-core >=1.43.0
Requires-Dist: azureml-mlflow >=1.47.0
Requires-Dist: azureml-metrics[all]
Requires-Dist: scikit-learn >=0.24.0
Requires-Dist: cryptography
Requires-Dist: python-dateutil <3.0.0,>=2.7.3
Requires-Dist: datasets >=2.11.0
Requires-Dist: soundfile >=0.12.1
Requires-Dist: librosa
Requires-Dist: diffusers >=0.15.0
Requires-Dist: sentencepiece
Requires-Dist: transformers >=4.28.1
Requires-Dist: torch >=1.9.0
Requires-Dist: accelerate >=0.19.0
Requires-Dist: Pillow >=10.0.1
Provides-Extra: deployments
Requires-Dist: flask ; extra == 'deployments'
Requires-Dist: numpy ; extra == 'deployments'
Requires-Dist: pandas ; extra == 'deployments'
